StellarInfra/DirManage.py
StellarInfra/IO.py
StellarInfra/Logger.py
StellarInfra/StageControl.py
StellarInfra/__init__.py
StellarInfra-0.0.4.dist-info/LICENSE
StellarInfra-0.0.4.dist-info/METADATA
StellarInfra-0.0.4.dist-info/WHEEL
StellarInfra-0.0.4.dist-info/top_level.txt
StellarInfra-0.0.4.dist-info/RECORD
