Metadata-Version: 2.1
Name: StellarInfra
Version: 0.0.4
Summary: An python infrastructure of StellarBlocks's software
Home-page: https://github.com/StellarBlocks/StellarInfra
Author: Powerfulbean
Author-email: powerfulbean@gmail.com
License: UNKNOWN
Platform: UNKNOWN
Classifier: Programming Language :: Python :: 3
Classifier: License :: OSI Approved :: MIT License
Classifier: Operating System :: OS Independent
